pyecore/__init__.py
pyecore/behavior.py
pyecore/commands.py
pyecore/ecore.py
pyecore/innerutils.py
pyecore/notification.py
pyecore/ordered_set_patch.py
pyecore/utils.py
pyecore/valuecontainer.py
pyecore/resources/__init__.py
pyecore/resources/json.py
pyecore/resources/resource.py
pyecore/resources/xmi.py
pyecore/type/__init__.py
pyecore/type/type.py
pyecore-0.15.2.dist-info/LICENSE
pyecore-0.15.2.dist-info/METADATA
pyecore-0.15.2.dist-info/WHEEL
pyecore-0.15.2.dist-info/top_level.txt
pyecore-0.15.2.dist-info/RECORD
