Metadata-Version: 2.1
Name: pyecore
Version: 0.15.2
Summary: A Python(ic) Implementation of the Eclipse Modeling Framework (EMF/Ecore)
Home-page: https://github.com/pyecore/pyecore
Author: Vincent Aranega
Author-email: vincent.aranega@gmail.com
License: BSD 3-Clause
Keywords: model metamodel EMF Ecore MDE
Classifier: Development Status :: 5 - Production/Stable
Classifier: Programming Language :: Python
Classifier: Programming Language :: Python :: 3.8
Classifier: Programming Language :: Python :: 3.9
Classifier: Programming Language :: Python :: 3.10
Classifier: Programming Language :: Python :: 3.11
Classifier: Programming Language :: Python :: 3.12
Classifier: Operating System :: OS Independent
Classifier: Intended Audience :: Developers
Classifier: Topic :: Software Development
Classifier: Topic :: Software Development :: Libraries
Classifier: License :: OSI Approved :: BSD License
License-File: LICENSE
